[
  { "id": "R1", "question": "Saya adalah orang yang berpikir secara realistis", "code": "R", "category": "REALISTIC" },
  { "id": "R2", "question": "Saya adalah orang yang mandiri", "code": "R", "category": "REALISTIC" },
  { "id": "R3", "question": "Saya adalah orang yang jujur", "code": "R", "category": "REALISTIC" },
  { "id": "R4", "question": "Saya adalah orang yang suka olahraga", "code": "R", "category": "REALISTIC" },
  { "id": "R5", "question": "Saya adalah orang yang cinta alam, hewan, dan tumbuhan", "code": "R", "category": "REALISTIC" },
  { "id": "R6", "question": "Saya bisa memperbaiki peralatan dan mesin listrik", "code": "R", "category": "REALISTIC" },
  { "id": "R7", "question": "Saya bisa membaca gambar dan desain", "code": "R", "category": "REALISTIC" },
  { "id": "R8", "question": "Saya bisa melakukan 1 jenis olahraga", "code": "R", "category": "REALISTIC" },
  { "id": "R9", "question": "Saya bisa mengoperasikan mesin dan peralatan", "code": "R", "category": "REALISTIC" },
  { "id": "R10", "question": "Saya bisa melakukan pekerjaan manual (memotong, merakit, merekatkan, dsb)", "code": "R", "category": "REALISTIC" },
  { "id": "R11", "question": "Saya suka bekerja di luar ruangan daripada duduk di dalam ruangan", "code": "R", "category": "REALISTIC" },
  { "id": "R12", "question": "Saya suka perakitan furnitur (menyusun meja, lemari, dsb)", "code": "R", "category": "REALISTIC" },
  { "id": "R13", "question": "Saya suka menanam pohon, berkebun", "code": "R", "category": "REALISTIC" },
  { "id": "R14", "question": "Saya suka menggunakan tangan dan kaki untuk bekerja", "code": "R", "category": "REALISTIC" },
  { "id": "R15", "question": "Saya suka membuat kerajinan tangan (merajut, menjahit, dsb)", "code": "R", "category": "REALISTIC" },

  { "id": "I1", "question": "Saya adalah orang yang punya kemampuan analisis yang tinggi", "code": "I", "category": "INVESTIGATIVE" },
  { "id": "I2", "question": "Saya adalah orang yang punya pengamatan yang baik", "code": "I", "category": "INVESTIGATIVE" },
  { "id": "I3", "question": "Saya adalah orang yang punya pemikiran logis", "code": "I", "category": "INVESTIGATIVE" },
  { "id": "I4", "question": "Saya adalah orang yang berhati-hati dalam segala hal, tepat waktu", "code": "I", "category": "INVESTIGATIVE" },
  { "id": "I5", "question": "Saya adalah orang yang punya wawasan yang luas", "code": "I", "category": "INVESTIGATIVE" },
  { "id": "I6", "question": "Saya bisa melakukan eksperimen dan penelitian", "code": "I", "category": "INVESTIGATIVE" },
  { "id": "I7", "question": "Saya bisa memikirkan dan memahami masalah yang kompleks dan abstrak", "code": "I", "category": "INVESTIGATIVE" },
  { "id": "I8", "question": "Saya bisa analisis data dan menyelesaikan masalah matematika dengan baik", "code": "I", "category": "INVESTIGATIVE" },
  { "id": "I9", "question": "Saya bisa berpikir secara koheren", "code": "I", "category": "INVESTIGATIVE" },
  { "id": "I10", "question": "Saya bisa cepat memahami ilmu pengetahuan, fisika, matematika, dan lain-lain", "code": "I", "category": "INVESTIGATIVE" },
  { "id": "I11", "question": "Saya suka bekerja sendiri", "code": "I", "category": "INVESTIGATIVE" },
  { "id": "I12", "question": "Saya suka kegiatan investigasi, inspeksi, evaluasi, dan sejenisnya", "code": "I", "category": "INVESTIGATIVE" },
  { "id": "I13", "question": "Saya suka bertanya", "code": "I", "category": "INVESTIGATIVE" },
  { "id": "I14", "question": "Saya suka mengunjungi laboratorium, museum sains, atau fasilitas ilmiah lainnya", "code": "I", "category": "INVESTIGATIVE" },
  { "id": "I15", "question": "Saya suka membaca buku, surat kabar, dan dokumen ilmiah atau teknis khusus", "code": "I", "category": "INVESTIGATIVE" },

  { "id": "A1", "question": "Saya adalah orang yang sangat kreatif", "code": "A", "category": "ARTISTIC" },
  { "id": "A2", "question": "Saya adalah orang yang memiliki imajinasi yang tinggi", "code": "A", "category": "ARTISTIC" },
  { "id": "A3", "question": "Saya adalah orang yang sensitif, emosional", "code": "A", "category": "ARTISTIC" },
  { "id": "A4", "question": "Saya adalah orang yang tidak ragu mengungkapkan pendapat", "code": "A", "category": "ARTISTIC" },
  { "id": "A5", "question": "Saya adalah orang yang individualis", "code": "A", "category": "ARTISTIC" },
  { "id": "A6", "question": "Saya bisa bernyanyi/berdansa/berakting dengan baik", "code": "A", "category": "ARTISTIC" },
  { "id": "A7", "question": "Saya bisa menggambar atau mengambil foto dengan baik", "code": "A", "category": "ARTISTIC" },
  { "id": "A8", "question": "Saya bisa memainkan instrumen musik", "code": "A", "category": "ARTISTIC" },
  { "id": "A9", "question": "Saya bisa berbicara di depan orang atau presentasi dengan percaya diri", "code": "A", "category": "ARTISTIC" },
  { "id": "A10", "question": "Saya bisa desain dan penataan (fashion/pakaian, desain interior, dsb)", "code": "A", "category": "ARTISTIC" },
  { "id": "A11", "question": "Saya suka kebebasan, tidak suka dibatasi", "code": "A", "category": "ARTISTIC" },
  { "id": "A12", "question": "Saya suka membaca cerita dan puisi", "code": "A", "category": "ARTISTIC" },
  { "id": "A13", "question": "Saya suka menggambar, mengambil foto, merekam", "code": "A", "category": "ARTISTIC" },
  { "id": "A14", "question": "Saya suka menonton drama, pameran seni, mendengarkan musik", "code": "A", "category": "ARTISTIC" },
  { "id": "A15", "question": "Saya suka pekerjaan yang memerlukan kreativitas", "code": "A", "category": "ARTISTIC" },

  { "id": "S1", "question": "Saya adalah orang yang ramah, mudah didekati, senang membantu", "code": "S", "category": "SOCIAL" },
  { "id": "S2", "question": "Saya adalah orang yang sopan", "code": "S", "category": "SOCIAL" },
  { "id": "S3", "question": "Saya adalah orang yang mau mendengar orang lain", "code": "S", "category": "SOCIAL" },
  { "id": "S4", "question": "Saya adalah orang yang simpatik", "code": "S", "category": "SOCIAL" },
  { "id": "S5", "question": "Saya adalah orang yang ingin berguna bagi masyarakat dan komunitas", "code": "S", "category": "SOCIAL" },
  { "id": "S6", "question": "Saya bisa membimbing dan mengajar orang lain", "code": "S", "category": "SOCIAL" },
  { "id": "S7", "question": "Saya bisa menengahi dan menyelesaikan konflik", "code": "S", "category": "SOCIAL" },
  { "id": "S8", "question": "Saya bisa bekerja sama dalam tim dengan baik", "code": "S", "category": "SOCIAL" },
  { "id": "S9", "question": "Saya bisa mengekspresikan emosi dengan jelas dan wajar", "code": "S", "category": "SOCIAL" },
  { "id": "S10", "question": "Saya bisa merencanakan dan memantau sebuah project atau kegiatan", "code": "S", "category": "SOCIAL" },
  { "id": "S11", "question": "Saya suka membantu orang lain memecahkan masalah", "code": "S", "category": "SOCIAL" },
  { "id": "S12", "question": "Saya suka bertemu dan bekerja dengan orang banyak", "code": "S", "category": "SOCIAL" },
  { "id": "S13", "question": "Saya suka berkontribusi dalam sebuah diskusi (ikut beropini)", "code": "S", "category": "SOCIAL" },
  { "id": "S14", "question": "Saya suka melakukan pekerjaan sukarela", "code": "S", "category": "SOCIAL" },
  { "id": "S15", "question": "Saya suka mendengarkan, membimbing, menasihati, dan menjelaskan sesuatu pada orang lain", "code": "S", "category": "SOCIAL" },

  { "id": "E1", "question": "Saya adalah orang yang yakin dengan keputusan sendiri", "code": "E", "category": "ENTERPRISING" },
  { "id": "E2", "question": "Saya adalah orang yang dinamis, antusias", "code": "E", "category": "ENTERPRISING" },
  { "id": "E3", "question": "Saya adalah orang yang ambisius", "code": "E", "category": "ENTERPRISING" },
  { "id": "E4", "question": "Saya adalah orang yang populer di sekolah/kampus", "code": "E", "category": "ENTERPRISING" },
  { "id": "E5", "question": "Saya adalah orang yang suka berteman dengan orang baru", "code": "E", "category": "ENTERPRISING" },
  { "id": "E6", "question": "Saya bisa meyakinkan orang lain dengan mudah", "code": "E", "category": "ENTERPRISING" },
  { "id": "E7", "question": "Saya bisa berekspresi dan berargumen dengan baik", "code": "E", "category": "ENTERPRISING" },
  { "id": "E8", "question": "Saya bisa memimpin sebuah kelompok", "code": "E", "category": "ENTERPRISING" },
  { "id": "E9", "question": "Saya bisa menemukan ide baru dan memulai sebuah project atau kegiatan", "code": "E", "category": "ENTERPRISING" },
  { "id": "E10", "question": "Saya bisa menyusun strategi untuk mencapai sebuah tujuan", "code": "E", "category": "ENTERPRISING" },
  { "id": "E11", "question": "Saya suka memiliki hak atau kewenangan atas kekuasaan, manajemen, atau evaluasi", "code": "E", "category": "ENTERPRISING" },
  { "id": "E12", "question": "Saya suka mempengaruhi orang lain dalam mengambil keputusan", "code": "E", "category": "ENTERPRISING" },
  { "id": "E13", "question": "Saya suka ketika orang lain menghormati dan mengagumi saya", "code": "E", "category": "ENTERPRISING" },
  { "id": "E14", "question": "Saya suka menghadapi risiko dan tantangan", "code": "E", "category": "ENTERPRISING" },
  { "id": "E15", "question": "Saya suka berkompetisi dan menjadi lebih baik dari orang lain", "code": "E", "category": "ENTERPRISING" },

  { "id": "C1", "question": "Saya adalah orang yang akurat, dapat diandalkan", "code": "C", "category": "CONVENTIONAL" },
  { "id": "C2", "question": "Saya adalah orang yang rapi", "code": "C", "category": "CONVENTIONAL" },
  { "id": "C3", "question": "Saya adalah orang yang teliti", "code": "C", "category": "CONVENTIONAL" },
  { "id": "C4", "question": "Saya adalah orang yang bekerja sesuai prinsip dan prosedur", "code": "C", "category": "CONVENTIONAL" },
  { "id": "C5", "question": "Saya adalah orang yang berpikir secara terorganisasi (runtut)", "code": "C", "category": "CONVENTIONAL" },
  { "id": "C6", "question": "Saya bisa memperkirakan pendapatan dan pengeluaran secara akurat", "code": "C", "category": "CONVENTIONAL" },
  { "id": "C7", "question": "Saya bisa menulis laporan dan melakukan perhitungan dengan baik", "code": "C", "category": "CONVENTIONAL" },
  { "id": "C8", "question": "Saya bisa mengurus dokumen dengan cepat", "code": "C", "category": "CONVENTIONAL" },
  { "id": "C9", "question": "Saya bisa bekerja di perusahaan atau lembaga yang punya sistem teratur/baku", "code": "C", "category": "CONVENTIONAL" },
  { "id": "C10", "question": "Saya bisa menyelesaikan dengan baik tugas-tugas yang memerlukan ketelitian tinggi", "code": "C", "category": "CONVENTIONAL" },
  { "id": "C11", "question": "Saya suka merapikan atau mengatur tempat kerja dan tempat tinggal", "code": "C", "category": "CONVENTIONAL" },
  { "id": "C12", "question": "Saya suka menetapkan rencana atau tujuan hidup", "code": "C", "category": "CONVENTIONAL" },
  { "id": "C13", "question": "Saya suka menyusun jadwal dan mengikutinya", "code": "C", "category": "CONVENTIONAL" },
  { "id": "C14", "question": "Saya suka bekerja dengan angka dan data", "code": "C", "category": "CONVENTIONAL" },
  { "id": "C15", "question": "Saya suka pekerjaan yang berkaitan dengan menyimpan, mengklasifikasikan, atau memperbarui informasi", "code": "C", "category": "CONVENTIONAL" }
]